mrna_bench/__init__.py
mrna_bench/utils.py
mrna_bench/data_splitter/__init__.py
mrna_bench/data_splitter/chromosome_split.py
mrna_bench/data_splitter/data_splitter.py
mrna_bench/data_splitter/homology_split.py
mrna_bench/data_splitter/kmer_split.py
mrna_bench/data_splitter/sklearn_split.py
mrna_bench/data_splitter/split_catalog.py
mrna_bench/datasets/__init__.py
mrna_bench/datasets/benchmark_dataset.py
mrna_bench/datasets/dataset_catalog.py
mrna_bench/datasets/dataset_utils.py
mrna_bench/datasets/eclip_binding.py
mrna_bench/datasets/go_bio_proc.py
mrna_bench/datasets/go_cell_comp.py
mrna_bench/datasets/go_mol_func.py
mrna_bench/datasets/mrl_hl_lbkwk.py
mrna_bench/datasets/mrl_sample.py
mrna_bench/datasets/mrl_sugimoto.py
mrna_bench/datasets/prot_loc.py
mrna_bench/datasets/rna_hl_human.py
mrna_bench/datasets/rna_hl_mouse.py
mrna_bench/datasets/rna_loc_fazal.py
mrna_bench/datasets/rna_loc_ietswaart.py
mrna_bench/datasets/vep_traitgym.py
mrna_bench/embedder/__init__.py
mrna_bench/embedder/dataset_embedder.py
mrna_bench/embedder/embedder_utils.py
mrna_bench/linear_probe/__init__.py
mrna_bench/linear_probe/evaluator.py
mrna_bench/linear_probe/linear_probe.py
mrna_bench/linear_probe/linear_probe_builder.py
mrna_bench/linear_probe/persister.py
mrna_bench/loader/__init__.py
mrna_bench/loader/loader.py
mrna_bench/models/__init__.py
mrna_bench/models/codonbert.py
mrna_bench/models/dnabert.py
mrna_bench/models/dnabert_s.py
mrna_bench/models/embedding_model.py
mrna_bench/models/ernierna.py
mrna_bench/models/evo1.py
mrna_bench/models/evo2.py
mrna_bench/models/helix_mrna.py
mrna_bench/models/hyenadna.py
mrna_bench/models/model_catalog.py
mrna_bench/models/naive_baseline.py
mrna_bench/models/naive_mamba.py
mrna_bench/models/nucleotide_transformer.py
mrna_bench/models/orthrus.py
mrna_bench/models/rinalmo.py
mrna_bench/models/rnabert.py
mrna_bench/models/rnaernie.py
mrna_bench/models/rnafm.py
mrna_bench/models/rnamsm.py
mrna_bench/models/splicebert.py
mrna_bench/models/utrbert.py
mrna_bench-1.2.2.dist-info/licenses/LICENSE
mrna_bench-1.2.2.dist-info/METADATA
mrna_bench-1.2.2.dist-info/WHEEL
mrna_bench-1.2.2.dist-info/top_level.txt
mrna_bench-1.2.2.dist-info/RECORD
