Metadata-Version: 2.4
Name: mrna-bench
Version: 1.2.2
Summary: Benchmarking suite for mRNA property prediction.
Author-email: "Ruian (Ian) Shi" <ian.shi@mail.utoronto.ca>, Taykhoom Dalal <tid4007@med.cornell.edu>, Phil Fradkin <phil.fradkin@gmail.com>, Divya Koyyalagunta <dko4001@med.cornell.edu>
License: GNU AFFERO GENERAL PUBLIC LICENSE
Project-URL: Repository, https://github.com/morrislab/mRNABench
Keywords: mrna,genomic foundation model,benchmark
Classifier: Programming Language :: Python :: 3
Classifier: License :: OSI Approved :: GNU Affero General Public License v3 or later (AGPLv3+)
Classifier: Operating System :: Unix
Requires-Python: >=3.10
License-File: LICENSE
Requires-Dist: tqdm
Requires-Dist: PyYAML
Requires-Dist: scikit-learn
Requires-Dist: numpy<2
Requires-Dist: pandas<=2.2.2
Requires-Dist: requests
Requires-Dist: pyarrow
Requires-Dist: fastparquet
Requires-Dist: openpyxl
Provides-Extra: base-models
Requires-Dist: torch==2.2.2; extra == "base-models"
Requires-Dist: transformers==4.38.0; extra == "base-models"
Requires-Dist: flash-attn==2.7.4.post1; extra == "base-models"
Requires-Dist: mamba-ssm==1.2.0.post1; extra == "base-models"
Requires-Dist: rna-fm==0.2.2; extra == "base-models"
Requires-Dist: accelerate==1.8.1; extra == "base-models"
Requires-Dist: multimolecule==0.0.7; extra == "base-models"
Requires-Dist: evo-model==0.4; extra == "base-models"
Provides-Extra: dev
Requires-Dist: mypy; extra == "dev"
Requires-Dist: flake8; extra == "dev"
Requires-Dist: flake8-docstrings; extra == "dev"
Requires-Dist: pytest; extra == "dev"
Dynamic: license-file
